{
  "RunType": "HTTP",
  "Labels": "k8s_taewa_3lite-scaling-2-1",
  "StartTime": "2022-03-27T11:14:56.961451807Z",
  "RequestedQPS": "max",
  "RequestedDuration": "1m0s",
  "ActualQPS": 19076.115886344327,
  "ActualDuration": 60002990484,
  "NumThreads": 70,
  "Version": "1.19.0",
  "DurationHistogram": {
    "Count": 1144624,
    "Min": 0.000745344,
    "Max": 0.21305696,
    "Sum": 4199.7107422840045,
    "Avg": 0.0036690745103055717,
    "StdDev": 0.002202590102451749,
    "Data": [
      {
        "Start": 0.000745344,
        "End": 0.01,
        "Percent": 99.08633752219069,
        "Count": 1134166
      },
      {
        "Start": 0.01,
        "End": 0.02,
        "Percent": 99.75467926585499,
        "Count": 7650
      },
      {
        "Start": 0.02,
        "End": 0.03,
        "Percent": 99.90162708452732,
        "Count": 1682
      },
      {
        "Start": 0.03,
        "End": 0.04,
        "Percent": 99.95588070842477,
        "Count": 621
      },
      {
        "Start": 0.04,
        "End": 0.05,
        "Percent": 99.97859559121598,
        "Count": 260
      },
      {
        "Start": 0.05,
        "End": 0.06,
        "Percent": 99.98846782873677,
        "Count": 113
      },
      {
        "Start": 0.06,
        "End": 0.07,
        "Percent": 99.99266134555977,
        "Count": 48
      },
      {
        "Start": 0.07,
        "End": 0.08,
        "Percent": 99.99720432211801,
        "Count": 52
      },
      {
        "Start": 0.08,
        "End": 0.09,
        "Percent": 99.99973790519856,
        "Count": 29
      },
      {
        "Start": 0.1,
        "End": 0.11,
        "Percent": 99.99991263506618,
        "Count": 2
      },
      {
        "Start": 0.2,
        "End": 0.21305696,
        "Percent": 100,
        "Count": 1
      }
    ],
    "Percentiles": [
      {
        "Percentile": 50,
        "Value": 0.0054153359588560756
      },
      {
        "Percentile": 75,
        "Value": 0.007750336018226625
      },
      {
        "Percentile": 90,
        "Value": 0.009151336053848954
      },
      {
        "Percentile": 99,
        "Value": 0.009991936075222353
      },
      {
        "Percentile": 99.9,
        "Value": 0.029889274673008774
      }
    ]
  },
  "Exactly": 0,
  "Jitter": false,
  "RunID": 0,
  "RetCodes": {
    "200": 1144624
  },
  "Sizes": {
    "Count": 1144624,
    "Min": 210,
    "Max": 212,
    "Sum": 242660241,
    "Avg": 211.99995893848111,
    "StdDev": 0.006931740564004275,
    "Data": [
      {
        "Start": 210,
        "End": 212,
        "Percent": 100,
        "Count": 1144624
      }
    ],
    "Percentiles": null
  },
  "HeaderSizes": {
    "Count": 1144624,
    "Min": 157,
    "Max": 157,
    "Sum": 179705968,
    "Avg": 157,
    "StdDev": 0,
    "Data": [
      {
        "Start": 157,
        "End": 157,
        "Percent": 100,
        "Count": 1144624
      }
    ],
    "Percentiles": null
  },
  "URL": "http://a659cff8de6b94481ad903d6703d461f-762226497.us-east-1.elb.amazonaws.com:3000/?n=1",
  "SocketCount": 70,
  "AbortOn": 0
}
