{"time":"17-04-2022 08:34:35","readyReplicas":1,"replicas":1,"name":"taewa-deployment"}
{"time":"17-04-2022 08:35:35","readyReplicas":1,"replicas":1,"name":"taewa-deployment"}
{"time":"17-04-2022 08:36:37","readyReplicas":1,"replicas":1,"name":"taewa-deployment"}
{"time":"17-04-2022 08:37:38","readyReplicas":2,"replicas":2,"name":"taewa-deployment"}
{"time":"17-04-2022 08:38:39","readyReplicas":4,"replicas":4,"name":"taewa-deployment"}
{"time":"17-04-2022 08:39:40","readyReplicas":6,"replicas":6,"name":"taewa-deployment"}
{"time":"17-04-2022 08:40:41","readyReplicas":6,"replicas":6,"name":"taewa-deployment"}
{"time":"17-04-2022 08:41:42","readyReplicas":6,"replicas":6,"name":"taewa-deployment"}
{"time":"17-04-2022 08:42:43","readyReplicas":6,"replicas":6,"name":"taewa-deployment"}
{"time":"17-04-2022 08:43:45","readyReplicas":6,"replicas":6,"name":"taewa-deployment"}
{"time":"17-04-2022 08:44:46","readyReplicas":6,"replicas":6,"name":"taewa-deployment"}
{"time":"17-04-2022 08:45:47","readyReplicas":6,"replicas":6,"name":"taewa-deployment"}
{"time":"17-04-2022 08:46:48","readyReplicas":6,"replicas":6,"name":"taewa-deployment"}
{"time":"17-04-2022 08:47:49","readyReplicas":6,"replicas":6,"name":"taewa-deployment"}
{"time":"17-04-2022 08:48:50","readyReplicas":6,"replicas":6,"name":"taewa-deployment"}
{"time":"17-04-2022 08:49:51","readyReplicas":6,"replicas":6,"name":"taewa-deployment"}
{"time":"17-04-2022 08:50:53","readyReplicas":6,"replicas":6,"name":"taewa-deployment"}
{"time":"17-04-2022 08:51:54","readyReplicas":6,"replicas":6,"name":"taewa-deployment"}
{"time":"17-04-2022 08:52:55","readyReplicas":6,"replicas":6,"name":"taewa-deployment"}
{"time":"17-04-2022 08:53:56","readyReplicas":6,"replicas":6,"name":"taewa-deployment"}
{"time":"17-04-2022 08:54:58","readyReplicas":6,"replicas":6,"name":"taewa-deployment"}
{"time":"17-04-2022 08:55:59","readyReplicas":6,"replicas":6,"name":"taewa-deployment"}
{"time":"17-04-2022 08:57:00","readyReplicas":6,"replicas":6,"name":"taewa-deployment"}
{"time":"17-04-2022 08:58:01","readyReplicas":6,"replicas":6,"name":"taewa-deployment"}
{"time":"17-04-2022 08:59:02","readyReplicas":6,"replicas":6,"name":"taewa-deployment"}
{"time":"17-04-2022 09:00:04","readyReplicas":6,"replicas":6,"name":"taewa-deployment"}
{"time":"17-04-2022 09:01:05","readyReplicas":6,"replicas":6,"name":"taewa-deployment"}
{"time":"17-04-2022 09:02:06","readyReplicas":6,"replicas":6,"name":"taewa-deployment"}
{"time":"17-04-2022 09:03:07","readyReplicas":6,"replicas":6,"name":"taewa-deployment"}
{"time":"17-04-2022 09:04:09","readyReplicas":6,"replicas":6,"name":"taewa-deployment"}
{"time":"17-04-2022 09:05:10","readyReplicas":6,"replicas":6,"name":"taewa-deployment"}
{"time":"17-04-2022 09:06:12","readyReplicas":6,"replicas":6,"name":"taewa-deployment"}
{"time":"17-04-2022 09:07:13","readyReplicas":6,"replicas":6,"name":"taewa-deployment"}
{"time":"17-04-2022 09:08:14","readyReplicas":6,"replicas":6,"name":"taewa-deployment"}
{"time":"17-04-2022 09:09:15","readyReplicas":6,"replicas":6,"name":"taewa-deployment"}
{"time":"17-04-2022 09:10:16","readyReplicas":6,"replicas":6,"name":"taewa-deployment"}
{"time":"17-04-2022 09:11:18","readyReplicas":6,"replicas":6,"name":"taewa-deployment"}
{"time":"17-04-2022 09:12:19","readyReplicas":6,"replicas":6,"name":"taewa-deployment"}
{"time":"17-04-2022 09:13:20","readyReplicas":6,"replicas":6,"name":"taewa-deployment"}
{"time":"17-04-2022 09:14:21","readyReplicas":6,"replicas":6,"name":"taewa-deployment"}
{"time":"17-04-2022 09:15:23","readyReplicas":6,"replicas":6,"name":"taewa-deployment"}
{"time":"17-04-2022 09:16:24","readyReplicas":6,"replicas":6,"name":"taewa-deployment"}
{"time":"17-04-2022 09:17:25","readyReplicas":6,"replicas":6,"name":"taewa-deployment"}
{"time":"17-04-2022 09:18:26","readyReplicas":6,"replicas":6,"name":"taewa-deployment"}
{"time":"17-04-2022 09:19:28","readyReplicas":6,"replicas":6,"name":"taewa-deployment"}
{"time":"17-04-2022 09:20:29","readyReplicas":6,"replicas":6,"name":"taewa-deployment"}
{"time":"17-04-2022 09:21:30","readyReplicas":6,"replicas":6,"name":"taewa-deployment"}
{"time":"17-04-2022 09:22:32","readyReplicas":6,"replicas":6,"name":"taewa-deployment"}
{"time":"17-04-2022 09:23:33","readyReplicas":6,"replicas":6,"name":"taewa-deployment"}
{"time":"17-04-2022 09:24:34","readyReplicas":6,"replicas":6,"name":"taewa-deployment"}
{"time":"17-04-2022 09:25:35","readyReplicas":6,"replicas":6,"name":"taewa-deployment"}
{"time":"17-04-2022 09:26:37","readyReplicas":6,"replicas":6,"name":"taewa-deployment"}
{"time":"17-04-2022 09:27:38","readyReplicas":6,"replicas":6,"name":"taewa-deployment"}
{"time":"17-04-2022 09:28:39","readyReplicas":6,"replicas":6,"name":"taewa-deployment"}
{"time":"17-04-2022 09:29:40","readyReplicas":1,"replicas":1,"name":"taewa-deployment"}
{"time":"17-04-2022 09:30:42","readyReplicas":1,"replicas":1,"name":"taewa-deployment"}
{"time":"17-04-2022 09:31:43","readyReplicas":1,"replicas":1,"name":"taewa-deployment"}
{"time":"17-04-2022 09:32:44","readyReplicas":1,"replicas":1,"name":"taewa-deployment"}
{"time":"17-04-2022 09:33:45","readyReplicas":1,"replicas":1,"name":"taewa-deployment"}
{"time":"17-04-2022 09:34:46","readyReplicas":2,"replicas":3,"name":"taewa-deployment"}
{"time":"17-04-2022 09:35:48","readyReplicas":4,"replicas":4,"name":"taewa-deployment"}
{"time":"17-04-2022 09:36:49","readyReplicas":4,"replicas":6,"name":"taewa-deployment"}
{"time":"17-04-2022 09:37:50","readyReplicas":4,"replicas":6,"name":"taewa-deployment"}
{"time":"17-04-2022 09:38:51","readyReplicas":4,"replicas":6,"name":"taewa-deployment"}
{"time":"17-04-2022 09:39:52","readyReplicas":6,"replicas":6,"name":"taewa-deployment"}
{"time":"17-04-2022 09:40:54","readyReplicas":6,"replicas":6,"name":"taewa-deployment"}
{"time":"17-04-2022 09:41:55","readyReplicas":6,"replicas":6,"name":"taewa-deployment"}
{"time":"17-04-2022 09:42:56","readyReplicas":6,"replicas":6,"name":"taewa-deployment"}
{"time":"17-04-2022 09:43:57","readyReplicas":6,"replicas":6,"name":"taewa-deployment"}
{"time":"17-04-2022 09:44:59","readyReplicas":6,"replicas":6,"name":"taewa-deployment"}
{"time":"17-04-2022 09:46:00","readyReplicas":6,"replicas":6,"name":"taewa-deployment"}
{"time":"17-04-2022 09:47:01","readyReplicas":6,"replicas":6,"name":"taewa-deployment"}
{"time":"17-04-2022 09:48:03","readyReplicas":6,"replicas":6,"name":"taewa-deployment"}
{"time":"17-04-2022 09:49:04","readyReplicas":1,"replicas":1,"name":"taewa-deployment"}
{"time":"17-04-2022 09:50:05","readyReplicas":1,"replicas":1,"name":"taewa-deployment"}
{"time":"17-04-2022 09:51:06","readyReplicas":1,"replicas":1,"name":"taewa-deployment"}
{"time":"17-04-2022 09:52:08","readyReplicas":1,"replicas":1,"name":"taewa-deployment"}
{"time":"17-04-2022 09:53:09","readyReplicas":2,"replicas":3,"name":"taewa-deployment"}
{"time":"17-04-2022 09:54:10","readyReplicas":4,"replicas":4,"name":"taewa-deployment"}
{"time":"17-04-2022 09:55:11","readyReplicas":4,"replicas":6,"name":"taewa-deployment"}
{"time":"17-04-2022 09:56:12","readyReplicas":6,"replicas":6,"name":"taewa-deployment"}
{"time":"17-04-2022 09:57:14","readyReplicas":6,"replicas":6,"name":"taewa-deployment"}
{"time":"17-04-2022 09:58:15","readyReplicas":6,"replicas":6,"name":"taewa-deployment"}
{"time":"17-04-2022 09:59:16","readyReplicas":6,"replicas":6,"name":"taewa-deployment"}
{"time":"17-04-2022 10:00:17","readyReplicas":6,"replicas":6,"name":"taewa-deployment"}
{"time":"17-04-2022 10:01:19","readyReplicas":6,"replicas":6,"name":"taewa-deployment"}
{"time":"17-04-2022 10:02:20","readyReplicas":6,"replicas":6,"name":"taewa-deployment"}
{"time":"17-04-2022 10:03:21","readyReplicas":6,"replicas":6,"name":"taewa-deployment"}
{"time":"17-04-2022 10:04:22","readyReplicas":6,"replicas":6,"name":"taewa-deployment"}
{"time":"17-04-2022 10:05:24","readyReplicas":6,"replicas":6,"name":"taewa-deployment"}
{"time":"17-04-2022 10:06:25","readyReplicas":1,"replicas":1,"name":"taewa-deployment"}
{"time":"17-04-2022 10:07:26","readyReplicas":1,"replicas":1,"name":"taewa-deployment"}
{"time":"17-04-2022 10:08:27","readyReplicas":1,"replicas":1,"name":"taewa-deployment"}
{"time":"17-04-2022 10:09:28","readyReplicas":1,"replicas":1,"name":"taewa-deployment"}
{"time":"17-04-2022 10:10:29","readyReplicas":1,"replicas":1,"name":"taewa-deployment"}
{"time":"17-04-2022 10:11:30","readyReplicas":2,"replicas":2,"name":"taewa-deployment"}
{"time":"17-04-2022 10:12:31","readyReplicas":2,"replicas":4,"name":"taewa-deployment"}
{"time":"17-04-2022 10:13:32","readyReplicas":2,"replicas":4,"name":"taewa-deployment"}
{"time":"17-04-2022 10:14:33","readyReplicas":4,"replicas":4,"name":"taewa-deployment"}
{"time":"17-04-2022 10:15:35","readyReplicas":4,"replicas":6,"name":"taewa-deployment"}
{"time":"17-04-2022 10:16:36","readyReplicas":4,"replicas":6,"name":"taewa-deployment"}
{"time":"17-04-2022 10:17:37","readyReplicas":4,"replicas":6,"name":"taewa-deployment"}
{"time":"17-04-2022 10:18:38","readyReplicas":6,"replicas":6,"name":"taewa-deployment"}
{"time":"17-04-2022 10:19:39","readyReplicas":6,"replicas":6,"name":"taewa-deployment"}
{"time":"17-04-2022 10:20:41","readyReplicas":6,"replicas":6,"name":"taewa-deployment"}
{"time":"17-04-2022 10:21:42","readyReplicas":6,"replicas":6,"name":"taewa-deployment"}
{"time":"17-04-2022 10:22:43","readyReplicas":6,"replicas":6,"name":"taewa-deployment"}
{"time":"17-04-2022 10:23:45","readyReplicas":6,"replicas":6,"name":"taewa-deployment"}
{"time":"17-04-2022 10:24:46","readyReplicas":6,"replicas":6,"name":"taewa-deployment"}
{"time":"17-04-2022 10:25:47","readyReplicas":6,"replicas":6,"name":"taewa-deployment"}
{"time":"17-04-2022 10:26:48","readyReplicas":6,"replicas":6,"name":"taewa-deployment"}
{"time":"17-04-2022 10:27:49","readyReplicas":6,"replicas":6,"name":"taewa-deployment"}
{"time":"17-04-2022 10:28:50","readyReplicas":6,"replicas":6,"name":"taewa-deployment"}
