{
  "RunType": "HTTP",
  "Labels": "k8s_taewa2_3-performance-chunk-26-3",
  "StartTime": "2022-05-22T03:49:56.303093134Z",
  "RequestedQPS": "max",
  "RequestedDuration": "1m0s",
  "ActualQPS": 5573.626872707259,
  "ActualDuration": 60004913791,
  "NumThreads": 25,
  "Version": "1.19.0",
  "DurationHistogram": {
    "Count": 334445,
    "Min": 0.001355325,
    "Max": 0.062949337,
    "Sum": 1499.9460482049994,
    "Avg": 0.004484881066259025,
    "StdDev": 0.0020226114027411795,
    "Data": [
      {
        "Start": 0.001355325,
        "End": 0.01,
        "Percent": 98.71189582741557,
        "Count": 330137
      },
      {
        "Start": 0.01,
        "End": 0.02,
        "Percent": 99.92196026252448,
        "Count": 4047
      },
      {
        "Start": 0.02,
        "End": 0.03,
        "Percent": 99.97877079938405,
        "Count": 190
      },
      {
        "Start": 0.03,
        "End": 0.04,
        "Percent": 99.99192692370943,
        "Count": 44
      },
      {
        "Start": 0.04,
        "End": 0.05,
        "Percent": 99.99760797739539,
        "Count": 19
      },
      {
        "Start": 0.05,
        "End": 0.06,
        "Percent": 99.99970099717443,
        "Count": 7
      },
      {
        "Start": 0.06,
        "End": 0.062949337,
        "Percent": 100,
        "Count": 1
      }
    ],
    "Percentiles": [
      {
        "Percentile": 50,
        "Value": 0.0057340523139327425
      },
      {
        "Percentile": 75,
        "Value": 0.007923429063495802
      },
      {
        "Percentile": 90,
        "Value": 0.009237055113233639
      },
      {
        "Percentile": 99,
        "Value": 0.012380899431677757
      },
      {
        "Percentile": 99.9,
        "Value": 0.01981851989127755
      }
    ]
  },
  "Exactly": 0,
  "Jitter": false,
  "RunID": 0,
  "RetCodes": {
    "200": 334445
  },
  "Sizes": {
    "Count": 334445,
    "Min": 209,
    "Max": 212,
    "Sum": 70901977,
    "Avg": 211.99891461974315,
    "StdDev": 0.036048359739754975,
    "Data": [
      {
        "Start": 209,
        "End": 212,
        "Percent": 100,
        "Count": 334445
      }
    ],
    "Percentiles": null
  },
  "HeaderSizes": {
    "Count": 334445,
    "Min": 157,
    "Max": 157,
    "Sum": 52507865,
    "Avg": 157,
    "StdDev": 0,
    "Data": [
      {
        "Start": 157,
        "End": 157,
        "Percent": 100,
        "Count": 334445
      }
    ],
    "Percentiles": null
  },
  "URL": "http://a664f49f2c42e4a7a8e648c0eaa57a40-358840911.us-east-1.elb.amazonaws.com:3000/?n=20000",
  "SocketCount": 25,
  "AbortOn": 0
}
