{
  "RunType": "HTTP",
  "Labels": "asg_raupi_3_70-scaling-3-8",
  "StartTime": "2022-06-04T20:36:46.620585031Z",
  "RequestedQPS": "max",
  "RequestedDuration": "1m0s",
  "ActualQPS": 1943.8981186854808,
  "ActualDuration": 60040183628,
  "NumThreads": 25,
  "Version": "1.19.0",
  "DurationHistogram": {
    "Count": 116712,
    "Min": 0.001657557,
    "Max": 3.015157657,
    "Sum": 1500.1454199480002,
    "Avg": 0.012853394851840429,
    "StdDev": 0.03389009233240896,
    "Data": [
      {
        "Start": 0.001657557,
        "End": 0.01,
        "Percent": 66.1380149427651,
        "Count": 77191
      },
      {
        "Start": 0.01,
        "End": 0.02,
        "Percent": 90.42857632462814,
        "Count": 28350
      },
      {
        "Start": 0.02,
        "End": 0.03,
        "Percent": 95.00479813558161,
        "Count": 5341
      },
      {
        "Start": 0.03,
        "End": 0.04,
        "Percent": 96.26602234560285,
        "Count": 1472
      },
      {
        "Start": 0.04,
        "End": 0.05,
        "Percent": 97.74144903694564,
        "Count": 1722
      },
      {
        "Start": 0.05,
        "End": 0.06,
        "Percent": 98.81246144355336,
        "Count": 1250
      },
      {
        "Start": 0.06,
        "End": 0.07,
        "Percent": 99.12519706628282,
        "Count": 365
      },
      {
        "Start": 0.07,
        "End": 0.08,
        "Percent": 99.206594009185,
        "Count": 95
      },
      {
        "Start": 0.08,
        "End": 0.09,
        "Percent": 99.26657070395504,
        "Count": 70
      },
      {
        "Start": 0.09,
        "End": 0.1,
        "Percent": 99.2931318116389,
        "Count": 31
      },
      {
        "Start": 0.1,
        "End": 0.11,
        "Percent": 99.31283843992048,
        "Count": 23
      },
      {
        "Start": 0.11,
        "End": 0.12,
        "Percent": 99.34625402700665,
        "Count": 39
      },
      {
        "Start": 0.12,
        "End": 0.14,
        "Percent": 99.43193501953526,
        "Count": 100
      },
      {
        "Start": 0.14,
        "End": 0.16,
        "Percent": 99.47563232572486,
        "Count": 51
      },
      {
        "Start": 0.16,
        "End": 0.18,
        "Percent": 99.55103159915005,
        "Count": 88
      },
      {
        "Start": 0.18,
        "End": 0.2,
        "Percent": 99.5972993351155,
        "Count": 54
      },
      {
        "Start": 0.2,
        "End": 0.25,
        "Percent": 99.6598464596614,
        "Count": 73
      },
      {
        "Start": 0.25,
        "End": 0.3,
        "Percent": 99.7712317499486,
        "Count": 130
      },
      {
        "Start": 0.3,
        "End": 0.35000000000000003,
        "Percent": 99.82778120501747,
        "Count": 66
      },
      {
        "Start": 0.35000000000000003,
        "End": 0.4,
        "Percent": 99.88604427993694,
        "Count": 68
      },
      {
        "Start": 0.4,
        "End": 0.45,
        "Percent": 99.9066077181438,
        "Count": 24
      },
      {
        "Start": 0.45,
        "End": 0.5,
        "Percent": 99.90917814791966,
        "Count": 3
      },
      {
        "Start": 0.5,
        "End": 0.6,
        "Percent": 99.94345054493111,
        "Count": 40
      },
      {
        "Start": 0.6,
        "End": 0.7000000000000001,
        "Percent": 99.95373226403454,
        "Count": 12
      },
      {
        "Start": 0.7000000000000001,
        "End": 0.8,
        "Percent": 99.96572760298855,
        "Count": 14
      },
      {
        "Start": 1,
        "End": 1.2,
        "Percent": 99.99914319007472,
        "Count": 39
      },
      {
        "Start": 3,
        "End": 3.015157657,
        "Percent": 100,
        "Count": 1
      }
    ],
    "Percentiles": [
      {
        "Percentile": 50,
        "Value": 0.007964374738891047
      },
      {
        "Percentile": 75,
        "Value": 0.013648324514991183
      },
      {
        "Percentile": 90,
        "Value": 0.01982356261022928
      },
      {
        "Percentile": 99,
        "Value": 0.06599671232876701
      },
      {
        "Percentile": 99.9,
        "Value": 0.4339333333333528
      }
    ]
  },
  "Exactly": 0,
  "Jitter": false,
  "RunID": 0,
  "RetCodes": {
    "200": 116712
  },
  "Sizes": {
    "Count": 116712,
    "Min": 174,
    "Max": 178,
    "Sum": 20773819,
    "Avg": 177.9921430529851,
    "StdDev": 0.0997716212573161,
    "Data": [
      {
        "Start": 174,
        "End": 178,
        "Percent": 100,
        "Count": 116712
      }
    ],
    "Percentiles": null
  },
  "HeaderSizes": {
    "Count": 116712,
    "Min": 134,
    "Max": 134,
    "Sum": 15639408,
    "Avg": 134,
    "StdDev": 0,
    "Data": [
      {
        "Start": 134,
        "End": 134,
        "Percent": 100,
        "Count": 116712
      }
    ],
    "Percentiles": null
  },
  "URL": "http://asg-1-lb-1488071781.us-east-1.elb.amazonaws.com:3000/?n=200",
  "SocketCount": 26,
  "AbortOn": 0
}
