{
  "RunType": "HTTP",
  "Labels": "asg_raupi_3_70-scaling-1-12",
  "StartTime": "2022-06-04T01:32:04.591209197Z",
  "RequestedQPS": "max",
  "RequestedDuration": "1m0s",
  "ActualQPS": 2080.6293103901735,
  "ActualDuration": 60019340964,
  "NumThreads": 25,
  "Version": "1.19.0",
  "DurationHistogram": {
    "Count": 124878,
    "Min": 0.001583441,
    "Max": 0.593509348,
    "Sum": 1500.1596445669993,
    "Avg": 0.012013001846338021,
    "StdDev": 0.01190755272917368,
    "Data": [
      {
        "Start": 0.001583441,
        "End": 0.01,
        "Percent": 55.70797097967616,
        "Count": 69567
      },
      {
        "Start": 0.01,
        "End": 0.02,
        "Percent": 88.57204631720559,
        "Count": 41040
      },
      {
        "Start": 0.02,
        "End": 0.03,
        "Percent": 96.49417831803841,
        "Count": 9893
      },
      {
        "Start": 0.03,
        "End": 0.04,
        "Percent": 98.20785086244175,
        "Count": 2140
      },
      {
        "Start": 0.04,
        "End": 0.05,
        "Percent": 98.98140585211166,
        "Count": 966
      },
      {
        "Start": 0.05,
        "End": 0.06,
        "Percent": 99.37458959944907,
        "Count": 491
      },
      {
        "Start": 0.06,
        "End": 0.07,
        "Percent": 99.48749979980461,
        "Count": 141
      },
      {
        "Start": 0.07,
        "End": 0.08,
        "Percent": 99.56757795608515,
        "Count": 100
      },
      {
        "Start": 0.08,
        "End": 0.09,
        "Percent": 99.64765611236567,
        "Count": 100
      },
      {
        "Start": 0.09,
        "End": 0.1,
        "Percent": 99.75175771553036,
        "Count": 130
      },
      {
        "Start": 0.1,
        "End": 0.11,
        "Percent": 99.80781242492672,
        "Count": 70
      },
      {
        "Start": 0.11,
        "End": 0.12,
        "Percent": 99.83664056118772,
        "Count": 36
      },
      {
        "Start": 0.12,
        "End": 0.14,
        "Percent": 99.88308589183043,
        "Count": 58
      },
      {
        "Start": 0.14,
        "End": 0.16,
        "Percent": 99.91351559121703,
        "Count": 38
      },
      {
        "Start": 0.16,
        "End": 0.18,
        "Percent": 99.9391406012268,
        "Count": 32
      },
      {
        "Start": 0.18,
        "End": 0.2,
        "Percent": 99.94474607216644,
        "Count": 7
      },
      {
        "Start": 0.2,
        "End": 0.25,
        "Percent": 99.97357420842742,
        "Count": 36
      },
      {
        "Start": 0.25,
        "End": 0.3,
        "Percent": 99.99359374749756,
        "Count": 25
      },
      {
        "Start": 0.3,
        "End": 0.35000000000000003,
        "Percent": 99.99679687374878,
        "Count": 4
      },
      {
        "Start": 0.5,
        "End": 0.593509348,
        "Percent": 100,
        "Count": 4
      }
    ],
    "Percentiles": [
      {
        "Percentile": 50,
        "Value": 0.00913760698398643
      },
      {
        "Percentile": 75,
        "Value": 0.015870248538011698
      },
      {
        "Percentile": 90,
        "Value": 0.021802486606691603
      },
      {
        "Percentile": 99,
        "Value": 0.05047291242362519
      },
      {
        "Percentile": 99.9,
        "Value": 0.1511168421052625
      }
    ]
  },
  "Exactly": 0,
  "Jitter": false,
  "RunID": 0,
  "RetCodes": {
    "200": 124878
  },
  "Sizes": {
    "Count": 124878,
    "Min": 174,
    "Max": 178,
    "Sum": 22227317,
    "Avg": 177.99225644228767,
    "StdDev": 0.09602653605108512,
    "Data": [
      {
        "Start": 174,
        "End": 178,
        "Percent": 100,
        "Count": 124878
      }
    ],
    "Percentiles": null
  },
  "HeaderSizes": {
    "Count": 124878,
    "Min": 134,
    "Max": 134,
    "Sum": 16733652,
    "Avg": 134,
    "StdDev": 0,
    "Data": [
      {
        "Start": 134,
        "End": 134,
        "Percent": 100,
        "Count": 124878
      }
    ],
    "Percentiles": null
  },
  "URL": "http://asg-1-lb-131401228.us-east-1.elb.amazonaws.com:3000/?n=200",
  "SocketCount": 25,
  "AbortOn": 0
}
