{
  "RunType": "HTTP",
  "Labels": "asg_raupi_3_70-performance-chunk-26-2",
  "StartTime": "2022-06-04T04:20:08.365738568Z",
  "RequestedQPS": "max",
  "RequestedDuration": "1m0s",
  "ActualQPS": 2975.031694567886,
  "ActualDuration": 60019528641,
  "NumThreads": 25,
  "Version": "1.19.0",
  "DurationHistogram": {
    "Count": 178560,
    "Min": 0.001312687,
    "Max": 0.653764417,
    "Sum": 1500.140346448001,
    "Avg": 0.008401323624820795,
    "StdDev": 0.01149092608631879,
    "Data": [
      {
        "Start": 0.001312687,
        "End": 0.01,
        "Percent": 77.43727598566308,
        "Count": 138272
      },
      {
        "Start": 0.01,
        "End": 0.02,
        "Percent": 94.89471326164875,
        "Count": 31172
      },
      {
        "Start": 0.02,
        "End": 0.03,
        "Percent": 97.80521953405018,
        "Count": 5197
      },
      {
        "Start": 0.03,
        "End": 0.04,
        "Percent": 98.61447132616487,
        "Count": 1445
      },
      {
        "Start": 0.04,
        "End": 0.05,
        "Percent": 99.2467517921147,
        "Count": 1129
      },
      {
        "Start": 0.05,
        "End": 0.06,
        "Percent": 99.53909050179212,
        "Count": 522
      },
      {
        "Start": 0.06,
        "End": 0.07,
        "Percent": 99.65781810035843,
        "Count": 212
      },
      {
        "Start": 0.07,
        "End": 0.08,
        "Percent": 99.75470430107526,
        "Count": 173
      },
      {
        "Start": 0.08,
        "End": 0.09,
        "Percent": 99.8258288530466,
        "Count": 127
      },
      {
        "Start": 0.09,
        "End": 0.1,
        "Percent": 99.85159050179212,
        "Count": 46
      },
      {
        "Start": 0.1,
        "End": 0.11,
        "Percent": 99.8616711469534,
        "Count": 18
      },
      {
        "Start": 0.11,
        "End": 0.12,
        "Percent": 99.87343189964157,
        "Count": 21
      },
      {
        "Start": 0.12,
        "End": 0.14,
        "Percent": 99.90143369175627,
        "Count": 50
      },
      {
        "Start": 0.14,
        "End": 0.16,
        "Percent": 99.90871415770609,
        "Count": 13
      },
      {
        "Start": 0.16,
        "End": 0.18,
        "Percent": 99.92495519713262,
        "Count": 29
      },
      {
        "Start": 0.18,
        "End": 0.2,
        "Percent": 99.93727598566308,
        "Count": 22
      },
      {
        "Start": 0.2,
        "End": 0.25,
        "Percent": 99.98319892473118,
        "Count": 82
      },
      {
        "Start": 0.25,
        "End": 0.3,
        "Percent": 99.98655913978494,
        "Count": 6
      },
      {
        "Start": 0.3,
        "End": 0.35000000000000003,
        "Percent": 99.99271953405018,
        "Count": 11
      },
      {
        "Start": 0.5,
        "End": 0.6,
        "Percent": 99.99327956989248,
        "Count": 1
      },
      {
        "Start": 0.6,
        "End": 0.653764417,
        "Percent": 100,
        "Count": 12
      }
    ],
    "Percentiles": [
      {
        "Percentile": 50,
        "Value": 0.006921922612145715
      },
      {
        "Percentile": 75,
        "Value": 0.009726571832300338
      },
      {
        "Percentile": 90,
        "Value": 0.017196201719491853
      },
      {
        "Percentile": 99,
        "Value": 0.046097431355181594
      },
      {
        "Percentile": 99.9,
        "Value": 0.13897600000000765
      }
    ]
  },
  "Exactly": 0,
  "Jitter": false,
  "RunID": 0,
  "RetCodes": {
    "200": 178560
  },
  "Sizes": {
    "Count": 178560,
    "Min": 174,
    "Max": 178,
    "Sum": 31782261,
    "Avg": 177.99205309139785,
    "StdDev": 0.09904685023087516,
    "Data": [
      {
        "Start": 174,
        "End": 178,
        "Percent": 100,
        "Count": 178560
      }
    ],
    "Percentiles": null
  },
  "HeaderSizes": {
    "Count": 178560,
    "Min": 134,
    "Max": 134,
    "Sum": 23927040,
    "Avg": 134,
    "StdDev": 0,
    "Data": [
      {
        "Start": 134,
        "End": 134,
        "Percent": 100,
        "Count": 178560
      }
    ],
    "Percentiles": null
  },
  "URL": "http://asg-1-lb-1615828183.us-east-1.elb.amazonaws.com:3000/?n=200",
  "SocketCount": 25,
  "AbortOn": 0
}
