{
  "RunType": "HTTP",
  "Labels": "asg_taewa_6-scaling-3-15",
  "StartTime": "2022-03-25T06:58:47.41570588Z",
  "RequestedQPS": "max",
  "RequestedDuration": "1m0s",
  "ActualQPS": 5319.207857137177,
  "ActualDuration": 60005551310,
  "NumThreads": 25,
  "Version": "1.19.0",
  "DurationHistogram": {
    "Count": 319182,
    "Min": 0.001344105,
    "Max": 0.063963753,
    "Sum": 1499.9720996600001,
    "Avg": 0.004699425718430237,
    "StdDev": 0.002294331388910221,
    "Data": [
      {
        "Start": 0.001344105,
        "End": 0.01,
        "Percent": 98.29188362752285,
        "Count": 313730
      },
      {
        "Start": 0.01,
        "End": 0.02,
        "Percent": 99.98652806235941,
        "Count": 5409
      },
      {
        "Start": 0.02,
        "End": 0.03,
        "Percent": 99.99185417724057,
        "Count": 17
      },
      {
        "Start": 0.03,
        "End": 0.04,
        "Percent": 99.99561378774493,
        "Count": 12
      },
      {
        "Start": 0.04,
        "End": 0.05,
        "Percent": 99.99624038949565,
        "Count": 2
      },
      {
        "Start": 0.05,
        "End": 0.06,
        "Percent": 99.99874679649855,
        "Count": 8
      },
      {
        "Start": 0.06,
        "End": 0.063963753,
        "Percent": 100,
        "Count": 4
      }
    ],
    "Percentiles": [
      {
        "Percentile": 50,
        "Value": 0.0057472500170369974
      },
      {
        "Percentile": 75,
        "Value": 0.007948836320733819
      },
      {
        "Percentile": 90,
        "Value": 0.009269788102951912
      },
      {
        "Percentile": 99,
        "Value": 0.014178554261416162
      },
      {
        "Percentile": 99.9,
        "Value": 0.01948940284710668
      }
    ]
  },
  "Exactly": 0,
  "Jitter": false,
  "RunID": 0,
  "RetCodes": {
    "200": 319182
  },
  "Sizes": {
    "Count": 319182,
    "Min": 209,
    "Max": 212,
    "Sum": 67666261,
    "Avg": 211.99898803817257,
    "StdDev": 0.0350748966020148,
    "Data": [
      {
        "Start": 209,
        "End": 212,
        "Percent": 100,
        "Count": 319182
      }
    ],
    "Percentiles": null
  },
  "HeaderSizes": {
    "Count": 319182,
    "Min": 157,
    "Max": 157,
    "Sum": 50111574,
    "Avg": 157,
    "StdDev": 0,
    "Data": [
      {
        "Start": 157,
        "End": 157,
        "Percent": 100,
        "Count": 319182
      }
    ],
    "Percentiles": null
  },
  "URL": "http://asg-1-lb-605904108.us-east-1.elb.amazonaws.com:3000/?n=20000",
  "SocketCount": 25,
  "AbortOn": 0
}
