{
  "RunType": "HTTP",
  "Labels": "k8s_apache2_3new-warmup-67",
  "StartTime": "2022-05-23T05:03:33.837813092Z",
  "RequestedQPS": "max",
  "RequestedDuration": "2m10s",
  "ActualQPS": 25970.549724632623,
  "ActualDuration": 130168750213,
  "NumThreads": 67,
  "Version": "1.19.0",
  "DurationHistogram": {
    "Count": 3380554,
    "Min": 0.000652286,
    "Max": 0.215173948,
    "Sum": 8709.222679524997,
    "Avg": 0.0025762708359413863,
    "StdDev": 0.002055817437303363,
    "Data": [
      {
        "Start": 0.000652286,
        "End": 0.01,
        "Percent": 99.16469312426307,
        "Count": 3352316
      },
      {
        "Start": 0.01,
        "End": 0.02,
        "Percent": 99.8784518750477,
        "Count": 24129
      },
      {
        "Start": 0.02,
        "End": 0.03,
        "Percent": 99.96772718317767,
        "Count": 3018
      },
      {
        "Start": 0.03,
        "End": 0.04,
        "Percent": 99.9857419819355,
        "Count": 609
      },
      {
        "Start": 0.04,
        "End": 0.05,
        "Percent": 99.99257518146435,
        "Count": 231
      },
      {
        "Start": 0.05,
        "End": 0.06,
        "Percent": 99.99529662889574,
        "Count": 92
      },
      {
        "Start": 0.06,
        "End": 0.07,
        "Percent": 99.9981364001285,
        "Count": 96
      },
      {
        "Start": 0.07,
        "End": 0.08,
        "Percent": 99.99931963814215,
        "Count": 40
      },
      {
        "Start": 0.08,
        "End": 0.09,
        "Percent": 99.99952670479453,
        "Count": 7
      },
      {
        "Start": 0.09,
        "End": 0.1,
        "Percent": 99.99961544764557,
        "Count": 3
      },
      {
        "Start": 0.2,
        "End": 0.215173948,
        "Percent": 100,
        "Count": 13
      }
    ],
    "Percentiles": [
      {
        "Percentile": 50,
        "Value": 0.005365511525961612
      },
      {
        "Percentile": 75,
        "Value": 0.007722125683160145
      },
      {
        "Percentile": 90,
        "Value": 0.009136094177479265
      },
      {
        "Percentile": 99,
        "Value": 0.009984475274070736
      },
      {
        "Percentile": 99.9,
        "Value": 0.022413671305500642
      }
    ]
  },
  "Exactly": 0,
  "Jitter": false,
  "RunID": 0,
  "RetCodes": {
    "200": 3380554
  },
  "Sizes": {
    "Count": 3380554,
    "Min": 270,
    "Max": 289,
    "Sum": 913384978,
    "Avg": 270.1879567668495,
    "StdDev": 1.8803858178390178,
    "Data": [
      {
        "Start": 270,
        "End": 289,
        "Percent": 100,
        "Count": 3380554
      }
    ],
    "Percentiles": null
  },
  "HeaderSizes": {
    "Count": 3380554,
    "Min": 225,
    "Max": 244,
    "Sum": 761260048,
    "Avg": 225.18795676684945,
    "StdDev": 1.8803858178414181,
    "Data": [
      {
        "Start": 225,
        "End": 225,
        "Percent": 99.01075385868707,
        "Count": 3347112
      },
      {
        "Start": 225,
        "End": 244,
        "Percent": 100,
        "Count": 33442
      }
    ],
    "Percentiles": null
  },
  "URL": "http://a4067ec32a9f64987883ce8b22c1880b-533834050.us-east-1.elb.amazonaws.com:80/",
  "SocketCount": 33507,
  "AbortOn": 0
}
