{
  "RunType": "HTTP",
  "Labels": "k8s_raupi2_3-scaling-1-1",
  "StartTime": "2022-05-28T22:28:33.055562667Z",
  "RequestedQPS": "max",
  "RequestedDuration": "1m0s",
  "ActualQPS": 1477.789059392328,
  "ActualDuration": 60013977933,
  "NumThreads": 25,
  "Version": "1.19.0",
  "DurationHistogram": {
    "Count": 88688,
    "Min": 0.002167915,
    "Max": 0.209328749,
    "Sum": 1500.1292065439995,
    "Avg": 0.016914680752119785,
    "StdDev": 0.010515625939050335,
    "Data": [
      {
        "Start": 0.002167915,
        "End": 0.01,
        "Percent": 8.551325996752661,
        "Count": 7584
      },
      {
        "Start": 0.01,
        "End": 0.02,
        "Percent": 75.36194299116002,
        "Count": 59253
      },
      {
        "Start": 0.02,
        "End": 0.03,
        "Percent": 96.04907090023453,
        "Count": 18347
      },
      {
        "Start": 0.03,
        "End": 0.04,
        "Percent": 97.6118527872993,
        "Count": 1386
      },
      {
        "Start": 0.04,
        "End": 0.05,
        "Percent": 98.32446328702868,
        "Count": 632
      },
      {
        "Start": 0.05,
        "End": 0.06,
        "Percent": 98.9446148295147,
        "Count": 550
      },
      {
        "Start": 0.06,
        "End": 0.07,
        "Percent": 99.20056828432257,
        "Count": 227
      },
      {
        "Start": 0.07,
        "End": 0.08,
        "Percent": 99.3663178784052,
        "Count": 147
      },
      {
        "Start": 0.08,
        "End": 0.09,
        "Percent": 99.57265920981418,
        "Count": 183
      },
      {
        "Start": 0.09,
        "End": 0.1,
        "Percent": 99.7778729929641,
        "Count": 182
      },
      {
        "Start": 0.1,
        "End": 0.11,
        "Percent": 99.8365055024355,
        "Count": 52
      },
      {
        "Start": 0.11,
        "End": 0.12,
        "Percent": 99.8658217571712,
        "Count": 26
      },
      {
        "Start": 0.12,
        "End": 0.14,
        "Percent": 99.94587768356486,
        "Count": 71
      },
      {
        "Start": 0.14,
        "End": 0.16,
        "Percent": 99.9639184557099,
        "Count": 16
      },
      {
        "Start": 0.16,
        "End": 0.18,
        "Percent": 99.96504600396896,
        "Count": 1
      },
      {
        "Start": 0.18,
        "End": 0.2,
        "Percent": 99.98308677611402,
        "Count": 16
      },
      {
        "Start": 0.2,
        "End": 0.209328749,
        "Percent": 100,
        "Count": 15
      }
    ],
    "Percentiles": [
      {
        "Percentile": 50,
        "Value": 0.016203905287495993
      },
      {
        "Percentile": 75,
        "Value": 0.019945825527821377
      },
      {
        "Percentile": 90,
        "Value": 0.027075925219381916
      },
      {
        "Percentile": 99,
        "Value": 0.062163876651982294
      },
      {
        "Percentile": 99.9,
        "Value": 0.12853859154929728
      }
    ]
  },
  "Exactly": 0,
  "Jitter": false,
  "RunID": 0,
  "RetCodes": {
    "200": 88688
  },
  "Sizes": {
    "Count": 88688,
    "Min": 174,
    "Max": 178,
    "Sum": 15785749,
    "Avg": 177.99193802994768,
    "StdDev": 0.09922778762816953,
    "Data": [
      {
        "Start": 174,
        "End": 178,
        "Percent": 100,
        "Count": 88688
      }
    ],
    "Percentiles": null
  },
  "HeaderSizes": {
    "Count": 88688,
    "Min": 134,
    "Max": 134,
    "Sum": 11884192,
    "Avg": 134,
    "StdDev": 0,
    "Data": [
      {
        "Start": 134,
        "End": 134,
        "Percent": 100,
        "Count": 88688
      }
    ],
    "Percentiles": null
  },
  "URL": "http://adce32dc672f543f8861de9aedd96ad1-549032164.us-east-1.elb.amazonaws.com:3000/?n=200",
  "SocketCount": 25,
  "AbortOn": 0
}
