{
  "RunType": "HTTP",
  "Labels": "asg_riwai_3-scaling-2-4",
  "StartTime": "2022-06-03T02:36:57.363243343Z",
  "RequestedQPS": "max",
  "RequestedDuration": "1m0s",
  "ActualQPS": 1542.7308056828062,
  "ActualDuration": 60015655135,
  "NumThreads": 25,
  "Version": "1.19.0",
  "DurationHistogram": {
    "Count": 92588,
    "Min": 0.001584366,
    "Max": 0.055583943,
    "Sum": 1500.1331394220006,
    "Avg": 0.016202241536937837,
    "StdDev": 0.004292145670416065,
    "Data": [
      {
        "Start": 0.001584366,
        "End": 0.01,
        "Percent": 0.48494405322504,
        "Count": 449
      },
      {
        "Start": 0.01,
        "End": 0.02,
        "Percent": 90.0419060785415,
        "Count": 82919
      },
      {
        "Start": 0.02,
        "End": 0.03,
        "Percent": 97.51371668034734,
        "Count": 6918
      },
      {
        "Start": 0.03,
        "End": 0.04,
        "Percent": 99.82287121441223,
        "Count": 2138
      },
      {
        "Start": 0.04,
        "End": 0.05,
        "Percent": 99.99459973214671,
        "Count": 159
      },
      {
        "Start": 0.05,
        "End": 0.055583943,
        "Percent": 100,
        "Count": 5
      }
    ],
    "Percentiles": [
      {
        "Percentile": 50,
        "Value": 0.015528889639286532
      },
      {
        "Percentile": 75,
        "Value": 0.01832040907391551
      },
      {
        "Percentile": 90,
        "Value": 0.019995320734692894
      },
      {
        "Percentile": 99,
        "Value": 0.03643648269410665
      },
      {
        "Percentile": 99.9,
        "Value": 0.04449132075471754
      }
    ]
  },
  "Exactly": 0,
  "Jitter": false,
  "RunID": 0,
  "RetCodes": {
    "200": 92588
  },
  "Sizes": {
    "Count": 92588,
    "Min": 270,
    "Max": 272,
    "Sum": 25183854,
    "Avg": 271.9991143560721,
    "StdDev": 0.032852232810288096,
    "Data": [
      {
        "Start": 270,
        "End": 272,
        "Percent": 100,
        "Count": 92588
      }
    ],
    "Percentiles": null
  },
  "HeaderSizes": {
    "Count": 92588,
    "Min": 228,
    "Max": 228,
    "Sum": 21110064,
    "Avg": 228,
    "StdDev": 0,
    "Data": [
      {
        "Start": 228,
        "End": 228,
        "Percent": 100,
        "Count": 92588
      }
    ],
    "Percentiles": null
  },
  "URL": "http://asg-1-lb-39485248.us-east-1.elb.amazonaws.com:3000/?n=20000",
  "SocketCount": 25,
  "AbortOn": 0
}
