{
  "RunType": "HTTP",
  "Labels": "asg_taewa_3-scaling-3-14",
  "StartTime": "2022-03-24T10:04:44.867413583Z",
  "RequestedQPS": "max",
  "RequestedDuration": "1m0s",
  "ActualQPS": 6336.948216324511,
  "ActualDuration": 60005855661,
  "NumThreads": 25,
  "Version": "1.19.0",
  "DurationHistogram": {
    "Count": 380254,
    "Min": 0.001078795,
    "Max": 0.052095935,
    "Sum": 1499.9442831390018,
    "Avg": 0.003944585153973401,
    "StdDev": 0.0020757464258357805,
    "Data": [
      {
        "Start": 0.001078795,
        "End": 0.01,
        "Percent": 95.24265359470249,
        "Count": 362164
      },
      {
        "Start": 0.01,
        "End": 0.02,
        "Percent": 99.94556270282496,
        "Count": 17883
      },
      {
        "Start": 0.02,
        "End": 0.03,
        "Percent": 99.98501001961847,
        "Count": 150
      },
      {
        "Start": 0.03,
        "End": 0.04,
        "Percent": 99.99500333987282,
        "Count": 38
      },
      {
        "Start": 0.04,
        "End": 0.05,
        "Percent": 99.99684421465652,
        "Count": 7
      },
      {
        "Start": 0.05,
        "End": 0.052095935,
        "Percent": 100,
        "Count": 12
      }
    ],
    "Percentiles": [
      {
        "Percentile": 50,
        "Value": 0.005762191762866445
      },
      {
        "Percentile": 75,
        "Value": 0.008103902460860164
      },
      {
        "Percentile": 90,
        "Value": 0.009508928879656398
      },
      {
        "Percentile": 99,
        "Value": 0.017989408935860866
      },
      {
        "Percentile": 99.9,
        "Value": 0.019903118045070743
      }
    ]
  },
  "Exactly": 0,
  "Jitter": false,
  "RunID": 0,
  "RetCodes": {
    "200": 380254
  },
  "Sizes": {
    "Count": 380254,
    "Min": 209,
    "Max": 212,
    "Sum": 80613488,
    "Avg": 211.99905326439696,
    "StdDev": 0.03345754758567894,
    "Data": [
      {
        "Start": 209,
        "End": 212,
        "Percent": 100,
        "Count": 380254
      }
    ],
    "Percentiles": null
  },
  "HeaderSizes": {
    "Count": 380254,
    "Min": 157,
    "Max": 157,
    "Sum": 59699878,
    "Avg": 157,
    "StdDev": 0,
    "Data": [
      {
        "Start": 157,
        "End": 157,
        "Percent": 100,
        "Count": 380254
      }
    ],
    "Percentiles": null
  },
  "URL": "http://asg-1-lb-1659640840.us-east-1.elb.amazonaws.com:3000/?n=20000",
  "SocketCount": 25,
  "AbortOn": 0
}
