{
  "RunType": "HTTP",
  "Labels": "asg_taewa_3-scaling-3-11",
  "StartTime": "2022-03-25T00:19:23.708147821Z",
  "RequestedQPS": "max",
  "RequestedDuration": "1m0s",
  "ActualQPS": 4144.235265445687,
  "ActualDuration": 60005763204,
  "NumThreads": 25,
  "Version": "1.19.0",
  "DurationHistogram": {
    "Count": 248678,
    "Min": 0.001270007,
    "Max": 0.222032179,
    "Sum": 1499.9741329060002,
    "Avg": 0.006031792651163353,
    "StdDev": 0.0026433555766856645,
    "Data": [
      {
        "Start": 0.001270007,
        "End": 0.01,
        "Percent": 97.17988724374493,
        "Count": 241665
      },
      {
        "Start": 0.01,
        "End": 0.02,
        "Percent": 99.87976419305286,
        "Count": 6714
      },
      {
        "Start": 0.02,
        "End": 0.03,
        "Percent": 99.95053844730937,
        "Count": 176
      },
      {
        "Start": 0.03,
        "End": 0.04,
        "Percent": 99.97908942487877,
        "Count": 71
      },
      {
        "Start": 0.04,
        "End": 0.05,
        "Percent": 99.99316385044114,
        "Count": 35
      },
      {
        "Start": 0.05,
        "End": 0.06,
        "Percent": 99.99557660910897,
        "Count": 6
      },
      {
        "Start": 0.06,
        "End": 0.07,
        "Percent": 99.9959787355536,
        "Count": 1
      },
      {
        "Start": 0.07,
        "End": 0.08,
        "Percent": 99.99678298844289,
        "Count": 2
      },
      {
        "Start": 0.2,
        "End": 0.222032179,
        "Percent": 100,
        "Count": 8
      }
    ],
    "Percentiles": [
      {
        "Percentile": 50,
        "Value": 0.005761656023578191
      },
      {
        "Percentile": 75,
        "Value": 0.008007498597621076
      },
      {
        "Percentile": 90,
        "Value": 0.009355004142046808
      },
      {
        "Percentile": 99,
        "Value": 0.0167414655942806
      },
      {
        "Percentile": 99.9,
        "Value": 0.022859204545455373
      }
    ]
  },
  "Exactly": 0,
  "Jitter": false,
  "RunID": 0,
  "RetCodes": {
    "200": 248678
  },
  "Sizes": {
    "Count": 248678,
    "Min": 209,
    "Max": 212,
    "Sum": 52719476,
    "Avg": 211.99895447124393,
    "StdDev": 0.036080417836062945,
    "Data": [
      {
        "Start": 209,
        "End": 212,
        "Percent": 100,
        "Count": 248678
      }
    ],
    "Percentiles": null
  },
  "HeaderSizes": {
    "Count": 248678,
    "Min": 157,
    "Max": 157,
    "Sum": 39042446,
    "Avg": 157,
    "StdDev": 0,
    "Data": [
      {
        "Start": 157,
        "End": 157,
        "Percent": 100,
        "Count": 248678
      }
    ],
    "Percentiles": null
  },
  "URL": "http://asg-1-lb-1816251612.us-east-1.elb.amazonaws.com:3000/?n=20000",
  "SocketCount": 25,
  "AbortOn": 0
}
