{
  "RunType": "HTTP",
  "Labels": "k8s_apache_3-warmup-66",
  "StartTime": "2022-03-25T01:10:10.408934843Z",
  "RequestedQPS": "max",
  "RequestedDuration": "2m10s",
  "ActualQPS": 24858.17426260266,
  "ActualDuration": 130008140013,
  "NumThreads": 66,
  "Version": "1.19.0",
  "DurationHistogram": {
    "Count": 3231765,
    "Min": 0.000960105,
    "Max": 1.005879715,
    "Sum": 8579.301989915004,
    "Avg": 0.0026546800246660895,
    "StdDev": 0.002687929114873309,
    "Data": [
      {
        "Start": 0.000960105,
        "End": 0.01,
        "Percent": 98.61329644946338,
        "Count": 3186950
      },
      {
        "Start": 0.01,
        "End": 0.02,
        "Percent": 99.81301239415613,
        "Count": 38772
      },
      {
        "Start": 0.02,
        "End": 0.03,
        "Percent": 99.94074445388202,
        "Count": 4128
      },
      {
        "Start": 0.03,
        "End": 0.04,
        "Percent": 99.96877867047883,
        "Count": 906
      },
      {
        "Start": 0.04,
        "End": 0.05,
        "Percent": 99.97902075181828,
        "Count": 331
      },
      {
        "Start": 0.05,
        "End": 0.06,
        "Percent": 99.98524026344737,
        "Count": 201
      },
      {
        "Start": 0.06,
        "End": 0.07,
        "Percent": 99.99006734709981,
        "Count": 156
      },
      {
        "Start": 0.07,
        "End": 0.08,
        "Percent": 99.99291408874099,
        "Count": 92
      },
      {
        "Start": 0.08,
        "End": 0.09,
        "Percent": 99.99393520259054,
        "Count": 33
      },
      {
        "Start": 0.09,
        "End": 0.1,
        "Percent": 99.99458500231297,
        "Count": 21
      },
      {
        "Start": 0.1,
        "End": 0.11,
        "Percent": 99.9948634879083,
        "Count": 9
      },
      {
        "Start": 0.11,
        "End": 0.12,
        "Percent": 99.9950800878158,
        "Count": 7
      },
      {
        "Start": 0.12,
        "End": 0.14,
        "Percent": 99.99566800185038,
        "Count": 19
      },
      {
        "Start": 0.14,
        "End": 0.16,
        "Percent": 99.9962868587289,
        "Count": 20
      },
      {
        "Start": 0.16,
        "End": 0.18,
        "Percent": 99.99650345863638,
        "Count": 7
      },
      {
        "Start": 0.18,
        "End": 0.2,
        "Percent": 99.9965344014803,
        "Count": 1
      },
      {
        "Start": 0.2,
        "End": 0.25,
        "Percent": 99.99996905715608,
        "Count": 111
      },
      {
        "Start": 1,
        "End": 1.005879715,
        "Percent": 100,
        "Count": 1
      }
    ],
    "Percentiles": [
      {
        "Percentile": 50,
        "Value": 0.005543610758153801
      },
      {
        "Percentile": 75,
        "Value": 0.007835365055498613
      },
      {
        "Percentile": 90,
        "Value": 0.0092104176339055
      },
      {
        "Percentile": 99,
        "Value": 0.013223292582275859
      },
      {
        "Percentile": 99.9,
        "Value": 0.026810162306201687
      }
    ]
  },
  "Exactly": 0,
  "Jitter": false,
  "RunID": 0,
  "RetCodes": {
    "200": 3231765
  },
  "Sizes": {
    "Count": 3231765,
    "Min": 270,
    "Max": 289,
    "Sum": 873183923,
    "Avg": 270.1879384794377,
    "StdDev": 1.880295252684448,
    "Data": [
      {
        "Start": 270,
        "End": 289,
        "Percent": 100,
        "Count": 3231765
      }
    ],
    "Percentiles": null
  },
  "HeaderSizes": {
    "Count": 3231765,
    "Min": 225,
    "Max": 244,
    "Sum": 727754498,
    "Avg": 225.18793847943772,
    "StdDev": 1.880295252684448,
    "Data": [
      {
        "Start": 225,
        "End": 225,
        "Percent": 99.0108501082226,
        "Count": 3199798
      },
      {
        "Start": 225,
        "End": 244,
        "Percent": 100,
        "Count": 31967
      }
    ],
    "Percentiles": null
  },
  "URL": "http://a198b71cdf71b47ef8bc3809513d11a5-2138676020.us-east-1.elb.amazonaws.com:80/",
  "SocketCount": 32031,
  "AbortOn": 0
}
